pycsvsql/__init__.py
pycsvsql/core.py
pycsvsql/helpers.py
pycsvsql-0.0.1.dist-info/METADATA
pycsvsql-0.0.1.dist-info/RECORD
pycsvsql-0.0.1.dist-info/WHEEL
pycsvsql-0.0.1.dist-info/top_level.txt
tests/__init__.py
tests/conftest.py
tests/test_basic.py
